EosDappHeyueKaifaZhiDiceYouxiXianshangWanzhengXiangmu/README.md
EosDappHeyueKaifaZhiDiceYouxiXianshangWanzhengXiangmu/__init__.py
EosDappHeyueKaifaZhiDiceYouxiXianshangWanzhengXiangmu/__main__.py
EosDappHeyueKaifaZhiDiceYouxiXianshangWanzhengXiangmu/file.epub
EosDappHeyueKaifaZhiDiceYouxiXianshangWanzhengXiangmu/index.html
EosDappHeyueKaifaZhiDiceYouxiXianshangWanzhengXiangmu/css/__init__.py
EosDappHeyueKaifaZhiDiceYouxiXianshangWanzhengXiangmu/css/annotations.css
EosDappHeyueKaifaZhiDiceYouxiXianshangWanzhengXiangmu/css/main.css
EosDappHeyueKaifaZhiDiceYouxiXianshangWanzhengXiangmu/css/normalize.css
EosDappHeyueKaifaZhiDiceYouxiXianshangWanzhengXiangmu/css/popup.css
EosDappHeyueKaifaZhiDiceYouxiXianshangWanzhengXiangmu/font/__init__.py
EosDappHeyueKaifaZhiDiceYouxiXianshangWanzhengXiangmu/font/fontello.eot
EosDappHeyueKaifaZhiDiceYouxiXianshangWanzhengXiangmu/font/fontello.svg
EosDappHeyueKaifaZhiDiceYouxiXianshangWanzhengXiangmu/font/fontello.ttf
EosDappHeyueKaifaZhiDiceYouxiXianshangWanzhengXiangmu/font/fontello.woff
EosDappHeyueKaifaZhiDiceYouxiXianshangWanzhengXiangmu/img/__init__.py
EosDappHeyueKaifaZhiDiceYouxiXianshangWanzhengXiangmu/img/annotator-glyph-sprite.png
EosDappHeyueKaifaZhiDiceYouxiXianshangWanzhengXiangmu/img/annotator-icon-sprite.png
EosDappHeyueKaifaZhiDiceYouxiXianshangWanzhengXiangmu/img/apple-touch-icon.png
EosDappHeyueKaifaZhiDiceYouxiXianshangWanzhengXiangmu/img/cancelfullscreen.png
EosDappHeyueKaifaZhiDiceYouxiXianshangWanzhengXiangmu/img/close.png
EosDappHeyueKaifaZhiDiceYouxiXianshangWanzhengXiangmu/img/fullscreen.png
EosDappHeyueKaifaZhiDiceYouxiXianshangWanzhengXiangmu/img/loader.gif
EosDappHeyueKaifaZhiDiceYouxiXianshangWanzhengXiangmu/img/menu-icon.png
EosDappHeyueKaifaZhiDiceYouxiXianshangWanzhengXiangmu/img/save.png
EosDappHeyueKaifaZhiDiceYouxiXianshangWanzhengXiangmu/img/saved.png
EosDappHeyueKaifaZhiDiceYouxiXianshangWanzhengXiangmu/img/settings-s.png
EosDappHeyueKaifaZhiDiceYouxiXianshangWanzhengXiangmu/img/settings.png
eos_dapp_heyue_kaifa_zhi_dice_youxi_xianshang_wanzheng_xiangmu-2024.3.4.0.dist-info/METADATA
eos_dapp_heyue_kaifa_zhi_dice_youxi_xianshang_wanzheng_xiangmu-2024.3.4.0.dist-info/WHEEL
eos_dapp_heyue_kaifa_zhi_dice_youxi_xianshang_wanzheng_xiangmu-2024.3.4.0.dist-info/entry_points.txt
eos_dapp_heyue_kaifa_zhi_dice_youxi_xianshang_wanzheng_xiangmu-2024.3.4.0.dist-info/top_level.txt
eos_dapp_heyue_kaifa_zhi_dice_youxi_xianshang_wanzheng_xiangmu-2024.3.4.0.dist-info/RECORD
